{
    "company": "GoFar Media",
    "doc_type": "Invoice",
    "form_data": {
        "M/s": "6999999999999999999999",
        "Campaign": "rewretre",
        "Date": "02-11-2025",
        "Invoice No": "GFM/34649174-4",
        "Invoice Month": "tetreert00000000000000000000000000000000000000",
        "line_items": [
            {
                "Description": "546465",
                "Campaign Start Date": "02-11-202502-11-202502-11-2025",
                "Campaign End Date": "02-11-202502-11-202502-11-2025",
                "Size": "etete",
                "Duration": "54654",
                "Amount": "64646"
            }
        ]
    }
}